coolors/__init__.py
coolors/main.py
coolors-0.1.4.dist-info/WHEEL
coolors-0.1.4.dist-info/METADATA
coolors-0.1.4.dist-info/RECORD
