Metadata-Version: 2.1
Name: coolors
Version: 0.1.4
Summary: generates 5 random colors by scraping coolors.co
Author: Arjun Gandhi
Author-email: account@arjugandhi.com
Requires-Python: >=3.7,<4.0
Classifier: Programming Language :: Python :: 3
Classifier: Programming Language :: Python :: 3.7
Classifier: Programming Language :: Python :: 3.8
Classifier: Programming Language :: Python :: 3.9
Requires-Dist: pyppeteer (>=0.2.5,<0.3.0)
